conda_vulnerability_scanner/__init__.py
conda_vulnerability_scanner/resources/__init__.py
conda_vulnerability_scanner/resources/binaries/__init__.py
conda_vulnerability_scanner/resources/binaries/cpe2cve.gz
conda_vulnerability_scanner/resources/binaries/go-cpe-dictionary.gz
conda_vulnerability_scanner/scanner.py
conda_vulnerability_scanner/version.py
conda_vulnerability_scanner-0.1.0.dist-info/LICENSE
conda_vulnerability_scanner-0.1.0.dist-info/WHEEL
conda_vulnerability_scanner-0.1.0.dist-info/METADATA
conda_vulnerability_scanner-0.1.0.dist-info/RECORD
