Metadata-Version: 2.1
Name: conda-vulnerability-scanner
Version: 0.1.0
Summary: Tool to scan for vulnerabilities in a conda environment.
Home-page: https://exasol.github.io/conda-vulnerability-scanner/main/
License: MIT
Keywords: conda,security,vulnerabilitiy scanner
Author: Exasol AG
Author-email: opensource@exasol.com
Requires-Python: >=3.8,<4.0
Classifier: License :: OSI Approved :: MIT License
Classifier: Programming Language :: Python :: 3
Classifier: Programming Language :: Python :: 3.8
Classifier: Programming Language :: Python :: 3.9
Classifier: Programming Language :: Python :: 3.10
Project-URL: Repository, https://github.com/exasol/conda-vulnerability-scanner
